auttitude/__init__.py
auttitude/api.py
auttitude/datamodels.py
auttitude/io.py
auttitude/math.py
auttitude/pandas_api.py
auttitude/plot.py
auttitude/stats.py
auttitude/applications/__init__.py
auttitude/applications/small_circles.py
auttitude/applications/stress.py
auttitude-0.1.4.dist-info/LICENSE
auttitude-0.1.4.dist-info/METADATA
auttitude-0.1.4.dist-info/WHEEL
auttitude-0.1.4.dist-info/top_level.txt
auttitude-0.1.4.dist-info/RECORD
