Metadata-Version: 2.1
Name: auttitude
Version: 0.1.4
Summary: library for analysis of structural geology data
Home-page: https://github.com/endarthur/autti
Author: Arthur Endlein
Author-email: endarthur@gmail.com
License: MIT
Keywords: geology attitude stereonet projection structural orientation
Platform: UNKNOWN
Classifier: Development Status :: 3 - Alpha
Classifier: Topic :: Utilities
Classifier: License :: OSI Approved :: MIT License
Requires-Dist: numpy
Requires-Dist: matplotlib
